{
	"format_version": "1.12.0",
	"minecraft:geometry": [
		{
			"description": {
				"identifier": "geometry.unknown",
				"texture_width": 64,
				"texture_height": 64,
				"visible_bounds_width": 2,
				"visible_bounds_height": 3.5,
				"visible_bounds_offset": [0, 1.25, 0]
			},
			"bones": [
				{
					"name": "striker",
					"pivot": [0, 0, -0.5]
				},
				{
					"name": "body",
					"parent": "striker",
					"pivot": [0, 12, 0]
				},
				{
					"name": "torso",
					"parent": "body",
					"pivot": [0, 12, 0],
					"cubes": [
						{
							"origin": [-4.5, 12.5, -3.5],
							"size": [9, 7, 5],
							"pivot": [0, 19.75, -0.5],
							"rotation": [-22.5, 0, 0],
							"uv": {
								"north": {"uv": [0, 12], "uv_size": [9, 7]},
								"east": {"uv": [28, 10], "uv_size": [5, 7]},
								"south": {"uv": [9, 12], "uv_size": [9, 7]},
								"west": {"uv": [28, 17], "uv_size": [5, 7]},
								"up": {"uv": [21, 0], "uv_size": [9, 5]},
								"down": {"uv": [21, 10], "uv_size": [9, -5]}
							}
						},
						{
							"origin": [-2.5, 17.16918, -4.86417],
							"size": [6, 4, 2],
							"pivot": [0.5, 19.16918, -2.36417],
							"rotation": [-30.09468, -4.32875, 2.50477],
							"uv": {
								"north": {"uv": [58, 0], "uv_size": [6, 4]},
								"east": {"uv": [56, 0], "uv_size": [2, 4]},
								"south": {"uv": [58, 4], "uv_size": [6, 4]},
								"west": {"uv": [56, 4], "uv_size": [2, 4]},
								"up": {"uv": [64, 10], "uv_size": [-6, -2]},
								"down": {"uv": [64, 12], "uv_size": [-6, -2]}
							}
						},
						{
							"origin": [-4, 13, -2.5],
							"size": [8, 12, 5],
							"uv": {
								"north": {"uv": [0, 0], "uv_size": [8, 12]},
								"east": {"uv": [16, 0], "uv_size": [5, 12]},
								"south": {"uv": [8, 0], "uv_size": [8, 12]},
								"west": {"uv": [18, 12], "uv_size": [5, 12]},
								"up": {"uv": [14, 24], "uv_size": [8, 5]},
								"down": {"uv": [22, 31], "uv_size": [8, -5]}
							}
						}
					]
				},
				{
					"name": "left_arm",
					"parent": "torso",
					"pivot": [4, 23, 0],
					"rotation": [0, 0, -12.5],
					"cubes": [
						{
							"origin": [4, 13, -2],
							"size": [3, 12, 4],
							"uv": {
								"north": {"uv": [61, 52], "uv_size": [3, 12]},
								"east": {"uv": [53, 52], "uv_size": [4, 12]},
								"south": {"uv": [50, 52], "uv_size": [3, 12]},
								"west": {"uv": [57, 52], "uv_size": [4, 12]},
								"up": {"uv": [36, 7], "uv_size": [3, 4]},
								"down": {"uv": [36, 15], "uv_size": [3, -4]}
							}
						}
					]
				},
				{
					"name": "right_arm",
					"parent": "torso",
					"pivot": [-4, 23, 0],
					"rotation": [0, 0, 12.5],
					"cubes": [
						{
							"origin": [-7, 13, -2],
							"size": [3, 12, 4],
							"uv": {
								"north": {"uv": [64, 52], "uv_size": [-3, 12]},
								"east": {"uv": [61, 52], "uv_size": [-4, 12]},
								"south": {"uv": [53, 52], "uv_size": [-3, 12]},
								"west": {"uv": [57, 52], "uv_size": [-4, 12]},
								"up": {"uv": [39, 7], "uv_size": [-3, 4]},
								"down": {"uv": [39, 15], "uv_size": [-3, -4]}
							}
						}
					]
				},
				{
					"name": "head",
					"parent": "torso",
					"pivot": [0, 25, 0],
					"cubes": [
						{
							"origin": [-3.5, 25, -2.5],
							"size": [7, 8, 5],
							"uv": {
								"north": {"uv": [0, 19], "uv_size": [7, 8]},
								"east": {"uv": [23, 10], "uv_size": [5, 8]},
								"south": {"uv": [7, 19], "uv_size": [7, 8]},
								"west": {"uv": [23, 18], "uv_size": [5, 8]},
								"up": {"uv": [0, 27], "uv_size": [7, 5]},
								"down": {"uv": [7, 32], "uv_size": [7, -5]}
							}
						},
						{
							"origin": [2.5, 25, -4.5],
							"size": [0, 2, 2],
							"pivot": [2.5, 25, -2.5],
							"rotation": [-45, 0, 0],
							"uv": {
								"north": {"uv": [0, 19], "uv_size": [7, 8]},
								"east": {"uv": [16, 30], "uv_size": [2, 2]},
								"south": {"uv": [7, 19], "uv_size": [7, 8]},
								"west": {"uv": [18, 30], "uv_size": [-2, 2]},
								"up": {"uv": [0, 27], "uv_size": [7, 5]},
								"down": {"uv": [7, 32], "uv_size": [7, -5]}
							}
						},
						{
							"origin": [-2.5, 25, -4.5],
							"size": [0, 2, 2],
							"pivot": [-2.5, 25, -2.5],
							"rotation": [-45, 0, 0],
							"uv": {
								"north": {"uv": [7, 19], "uv_size": [-7, 8]},
								"east": {"uv": [16, 30], "uv_size": [2, 2]},
								"south": {"uv": [14, 19], "uv_size": [-7, 8]},
								"west": {"uv": [18, 30], "uv_size": [-2, 2]},
								"up": {"uv": [7, 27], "uv_size": [-7, 5]},
								"down": {"uv": [14, 32], "uv_size": [-7, -5]}
							}
						},
						{
							"origin": [-1.5, 27, -4.5],
							"size": [0, 2, 2],
							"pivot": [-1.5, 27, -2.5],
							"rotation": [-45, 0, 0],
							"uv": {
								"north": {"uv": [7, 19], "uv_size": [-7, 8]},
								"east": {"uv": [16, 30], "uv_size": [2, 2]},
								"south": {"uv": [14, 19], "uv_size": [-7, 8]},
								"west": {"uv": [18, 30], "uv_size": [-2, 2]},
								"up": {"uv": [7, 27], "uv_size": [-7, 5]},
								"down": {"uv": [14, 32], "uv_size": [-7, -5]}
							}
						},
						{
							"origin": [1.5, 27, -4.5],
							"size": [0, 2, 2],
							"pivot": [1.5, 27, -2.5],
							"rotation": [-45, 0, 0],
							"uv": {
								"north": {"uv": [0, 19], "uv_size": [7, 8]},
								"east": {"uv": [16, 30], "uv_size": [2, 2]},
								"south": {"uv": [7, 19], "uv_size": [7, 8]},
								"west": {"uv": [18, 30], "uv_size": [-2, 2]},
								"up": {"uv": [0, 27], "uv_size": [7, 5]},
								"down": {"uv": [7, 32], "uv_size": [7, -5]}
							}
						},
						{
							"origin": [0.5, 30, -4.5],
							"size": [0, 2, 2],
							"pivot": [0.5, 30, -2.5],
							"rotation": [-67.5, 0, 0],
							"uv": {
								"north": {"uv": [0, 19], "uv_size": [7, 8]},
								"east": {"uv": [16, 30], "uv_size": [2, 2]},
								"south": {"uv": [7, 19], "uv_size": [7, 8]},
								"west": {"uv": [18, 30], "uv_size": [-2, 2]},
								"up": {"uv": [0, 27], "uv_size": [7, 5]},
								"down": {"uv": [7, 32], "uv_size": [7, -5]}
							}
						},
						{
							"origin": [-0.5, 30, -4.5],
							"size": [0, 2, 2],
							"pivot": [-0.5, 30, -2.5],
							"rotation": [-67.5, 0, 0],
							"uv": {
								"north": {"uv": [7, 19], "uv_size": [-7, 8]},
								"east": {"uv": [16, 30], "uv_size": [2, 2]},
								"south": {"uv": [14, 19], "uv_size": [-7, 8]},
								"west": {"uv": [18, 30], "uv_size": [-2, 2]},
								"up": {"uv": [7, 27], "uv_size": [-7, 5]},
								"down": {"uv": [14, 32], "uv_size": [-7, -5]}
							}
						}
					]
				},
				{
					"name": "left_leg",
					"parent": "body",
					"pivot": [2, 13, 0],
					"rotation": [0, 0, -2.5],
					"cubes": [
						{
							"origin": [0, 0, -2],
							"size": [4, 13, 4],
							"uv": {
								"north": {"uv": [4, 51], "uv_size": [4, 13]},
								"east": {"uv": [8, 51], "uv_size": [4, 13]},
								"south": {"uv": [12, 51], "uv_size": [4, 13]},
								"west": {"uv": [0, 51], "uv_size": [4, 13]},
								"up": {"uv": [14, 19], "uv_size": [4, 4]},
								"down": {"uv": [34, 39], "uv_size": [4, -4]}
							}
						}
					]
				},
				{
					"name": "right_leg",
					"parent": "body",
					"pivot": [-2, 13, 0],
					"rotation": [0, 0, 2.5],
					"cubes": [
						{
							"origin": [-4, 0, -2],
							"size": [4, 13, 4],
							"uv": {
								"north": {"uv": [8, 51], "uv_size": [-4, 13]},
								"east": {"uv": [4, 51], "uv_size": [-4, 13]},
								"south": {"uv": [16, 51], "uv_size": [-4, 13]},
								"west": {"uv": [12, 51], "uv_size": [-4, 13]},
								"up": {"uv": [18, 19], "uv_size": [-4, 4]},
								"down": {"uv": [38, 39], "uv_size": [-4, -4]}
							}
						}
					]
				},
				{
					"name": "medium_tongue",
					"pivot": [0, 0, 0]
				},
				{
					"name": "body2",
					"parent": "medium_tongue",
					"pivot": [0, 2.5, 2]
				},
				{
					"name": "seg1",
					"parent": "body2",
					"pivot": [0, 2.5, 2],
					"cubes": [
						{
							"origin": [-2, -10, -10],
							"size": [4, 5, 12],
							"inflate": 0.25,
							"uv": {
								"north": {"uv": [56, 36], "uv_size": [4, 5]},
								"east": {"uv": [38, 16], "uv_size": [12, 5]},
								"south": {"uv": [38, 38], "uv_size": [4, 5]},
								"west": {"uv": [38, 21], "uv_size": [12, 5]},
								"up": {"uv": [38, 26], "uv_size": [4, 12]},
								"down": {"uv": [42, 38], "uv_size": [4, -12]}
							}
						}
					]
				},
				{
					"name": "seg2",
					"parent": "seg1",
					"pivot": [0, 2.5, -10],
					"cubes": [
						{
							"origin": [-1.5, -9.5, -22],
							"size": [3, 4, 12],
							"inflate": 0.25,
							"uv": {
								"north": {"uv": [58, 26], "uv_size": [3, 4]},
								"east": {"uv": [46, 26], "uv_size": [12, 4]},
								"south": {"uv": [42, 38], "uv_size": [3, 4]},
								"west": {"uv": [50, 16], "uv_size": [12, 4]},
								"up": {"uv": [46, 30], "uv_size": [3, 12]},
								"down": {"uv": [49, 42], "uv_size": [3, -12]}
							}
						}
					]
				},
				{
					"name": "seg3",
					"parent": "seg2",
					"pivot": [0, 2.5, -22],
					"cubes": [
						{
							"origin": [-1, -9, -34],
							"size": [2, 3, 12],
							"inflate": 0.25,
							"uv": {
								"north": {"uv": [60, 36], "uv_size": [2, 3]},
								"east": {"uv": [50, 20], "uv_size": [12, 3]},
								"south": {"uv": [61, 26], "uv_size": [2, 3]},
								"west": {"uv": [50, 23], "uv_size": [12, 3]},
								"up": {"uv": [52, 36], "uv_size": [2, 12]},
								"down": {"uv": [54, 48], "uv_size": [2, -12]}
							}
						}
					]
				},
				{
					"name": "seg4",
					"parent": "seg3",
					"pivot": [0, 2.5, -34],
					"cubes": [
						{
							"origin": [0, -9, -46],
							"size": [0, 3, 12],
							"uv": {
								"north": {"uv": [38, 16], "uv_size": [0, 3]},
								"east": {"uv": [52, 30], "uv_size": [12, 3]},
								"south": {"uv": [38, 16], "uv_size": [0, 3]},
								"west": {"uv": [52, 33], "uv_size": [12, 3]},
								"up": {"uv": [38, 16], "uv_size": [0, 12]},
								"down": {"uv": [38, 28], "uv_size": [0, -12]}
							}
						}
					]
				}
			]
		}
	]
}